web_error/__init__.py
web_error/cors.py
web_error/error.py
web_error/handler/__init__.py
web_error/handler/fastapi.py
web_error/handler/starlette.py
web_error/handler/util.py
web_error-0.6.11.dist-info/LICENSE
web_error-0.6.11.dist-info/METADATA
web_error-0.6.11.dist-info/WHEEL
web_error-0.6.11.dist-info/RECORD
